README.rst
setup.py
../../metrique
metriqueu/__init__.py
metriqueu/celeryconfig.py
metriqueu/jsonconf.py
metriqueu/utils.py
metriqueu.egg-info/PKG-INFO
metriqueu.egg-info/SOURCES.txt
metriqueu.egg-info/dependency_links.txt
metriqueu.egg-info/requires.txt
metriqueu.egg-info/top_level.txt