Metadata-Version: 1.1
Name: metriqueu
Version: 0.2.7-1a
Summary: Metrique - Shared Utility Libraries
Home-page: https://github.com/drpoovilleorg/metrique
Author: Chris Ward
Author-email: cward@redhat.com
License: GPLv3
Download-URL: https://github.com/drpoovilleorg/metrique/archive/master.zip
Platform: UNKNOWN
Provides: metriqueu
